{
  "presets": {
    "single": {
      "count": 1,
      "label": "单张指引",
      "positions": [
        "指引"
      ],
      "positionDetails": [
        "这张牌是你此刻最需要的智慧"
      ],
      "description": "最简洁的牌阵，适合日常小事或快速获取灵感指引。一张牌直击核心，为你揭示当下最需要关注的能量。"
    },
    "two-choice": {
      "count": 2,
      "label": "二选一",
      "positions": [
        "选项A",
        "选项B"
      ],
      "positionDetails": [
        "选择A的结果和影响",
        "选择B的结果和影响"
      ],
      "description": "面临两个选择的决策牌阵。分别揭示每个选项的可能结果，帮你做出更明智的决定。"
    },
    "two-cause": {
      "count": 2,
      "label": "因果牌阵",
      "positions": [
        "原因",
        "结果"
      ],
      "positionDetails": [
        "造成当前局面的根本原因",
        "按照当前轨迹发展的结果"
      ],
      "description": "探究事情的因果关系。第一张牌揭示根源，第二张牌预示结果，适合分析问题的来龙去脉。"
    },
    "three": {
      "count": 3,
      "label": "三张牌阵",
      "positions": [
        "过去",
        "现在",
        "未来"
      ],
      "positionDetails": [
        "影响当前局面的根源或过去经历",
        "当下的处境和能量状态",
        "事态发展的趋势和可能性"
      ],
      "description": "经典时间线牌阵，展示事情的发展脉络。过去影响现在，现在塑造未来，帮助你理解事件的来龙去脉。"
    },
    "three-body": {
      "count": 3,
      "label": "身心灵",
      "positions": [
        "身体",
        "心理",
        "灵性"
      ],
      "positionDetails": [
        "身体健康和物质层面的状态",
        "情绪和心理层面的状态",
        "精神成长和内在智慧的状态"
      ],
      "description": "身心灵三位一体牌阵，从身体、心理、灵性三个层面全面审视你的状态，发现失衡之处。"
    },
    "four-elements": {
      "count": 4,
      "label": "四元素",
      "positions": [
        "火（行动）",
        "水（情感）",
        "风（思考）",
        "土（物质）"
      ],
      "positionDetails": [
        "行动力、热情和意志力的状态",
        "情感、直觉和人际关系的状态",
        "思想、沟通和决策的状态",
        "物质、财务和实际事务的状态"
      ],
      "description": "基于四元素的平衡牌阵。火代表行动，水代表情感，风代表思考，土代表物质，全面审视你生活的四个维度。"
    },
    "horseshoe": {
      "count": 5,
      "label": "马蹄牌阵",
      "positions": [
        "现状",
        "障碍",
        "潜意识",
        "近期",
        "结果"
      ],
      "positionDetails": [
        "你目前的处境",
        "当前面临的挑战或阻碍",
        "你可能未意识到的深层影响",
        "即将发生的事件或变化",
        "按照当前轨迹的可能结局"
      ],
      "description": "综合分析牌阵，适合需要深入理解的复杂问题。涵盖现状、障碍、内心潜意识、近期发展和最终结果五个维度。"
    },
    "relationship": {
      "count": 6,
      "label": "关系牌阵",
      "positions": [
        "你",
        "对方",
        "关系核心",
        "你的需求",
        "对方需求",
        "建议/结果"
      ],
      "positionDetails": [
        "你在这段关系中的状态和感受",
        "对方的状态和感受",
        "这段关系的本质和当前能量",
        "你内心真正渴望的",
        "对方内心真正渴望的",
        "关系的发展方向和建议"
      ],
      "description": "专为感情和人际关系设计。分别从你和对方的角度出发，揭示关系的核心动态、彼此需求，以及未来的建议方向。"
    },
    "seven-v": {
      "count": 7,
      "label": "V字七张",
      "positions": [
        "过去",
        "现在",
        "隐藏",
        "他人影响",
        "希望",
        "恐惧",
        "结果"
      ],
      "positionDetails": [
        "过去的经历和影响",
        "当前的处境和状态",
        "你没有意识到或忽略的因素",
        "其他人或外界对你的影响",
        "你内心期待的结果",
        "你内心害怕的事情",
        "最终的走向"
      ],
      "description": "V字型七张牌阵，比三张更深入。涵盖过去、现在、隐藏因素、他人影响、希望与恐惧，最终揭示结果。"
    },
    "celtic": {
      "count": 10,
      "label": "凯尔特十字",
      "positions": [
        "现况",
        "挑战",
        "根源",
        "过去",
        "可能",
        "近未来",
        "自我",
        "环境",
        "希望",
        "结局"
      ],
      "positionDetails": [
        "当前的核心处境",
        "你面临的障碍或对立力量",
        "造成现状的根本原因",
        "影响当下的过去经历",
        "最好的结果或潜力",
        "近期的发展趋势",
        "你如何看待自己",
        "外界的影响和他人看法",
        "你的期望或恐惧",
        "最终的走向"
      ],
      "description": "最全面深入的经典牌阵，适合重大人生议题。从现状到根源，从过去到未来，全方位剖析问题的各个层面。"
    }
  },
  "custom": []
}